integdb/__init__.py
integdb/controller.py
integdb/module/__init__.py
integdb/module/interface.py
integdb/module/mariadb.py
integdb/module/mssql.py
integdb/module/mysql.py
integdb/module/sqlalchemy.py
integ_db-0.1.1.dist-info/LICENSE
integ_db-0.1.1.dist-info/METADATA
integ_db-0.1.1.dist-info/WHEEL
integ_db-0.1.1.dist-info/top_level.txt
integ_db-0.1.1.dist-info/RECORD
