Metadata-Version: 2.1
Name: integ-db
Version: 0.1.1
Summary: This package Integrated Database library
Home-page: https://github.com/Byeongin-Jeong/integdb
Author: byeongin.jeong
Author-email: jbi0214@gmail.com
Project-URL: Bug Tracker, https://github.com/Byeongin-Jeong/integdb/issues
Keywords: mysql,mssql,mariadb,python db,python database,integrate database,sqlalchemy
Classifier: Programming Language :: Python :: 3
Classifier: Programming Language :: Python :: 3.6
Classifier: Programming Language :: Python :: 3.7
Classifier: Programming Language :: Python :: 3.8
Classifier: Programming Language :: Python :: 3.9
Classifier: Programming Language :: Python :: 3.10
Classifier: Programming Language :: Python :: 3.11
Classifier: Programming Language :: Python :: 3.12
Classifier: Intended Audience :: Developers
Classifier: License :: OSI Approved :: MIT License
Classifier: Topic :: Database
Requires-Python: >=3.6
License-File: LICENSE
Requires-Dist: pymysql
Requires-Dist: mariadb
Requires-Dist: pymssql
Requires-Dist: pymysql-pool
Requires-Dist: SQLAlchemy
Requires-Dist: pandas
